llama_api_bench/__init__.py
llama_api_bench/cli/__init__.py
llama_api_bench/cli/cli.py
llama_api_bench/core/__init__.py
llama_api_bench/core/interface.py
llama_api_bench/core/providers.py
llama_api_bench/core/run.py
llama_api_bench/core/criterias/__init__.py
llama_api_bench/core/criterias/basic.py
llama_api_bench/core/criterias/common.py
llama_api_bench/core/criterias/criterias.py
llama_api_bench/core/criterias/long_context.py
llama_api_bench/core/criterias/structured.py
llama_api_bench/core/criterias/tool_call.py
llama_api_bench/core/criterias/tool_response.py
llama_api_bench/core/criterias/usage.py
llama_api_bench/core/criterias/vision.py
llama_api_bench/data/__init__.py
llama_api_bench/data/basic.py
llama_api_bench/data/data.py
llama_api_bench/data/export.py
llama_api_bench/data/long_context.py
llama_api_bench/data/structured.py
llama_api_bench/data/tool_call.py
llama_api_bench/data/tool_response.py
llama_api_bench/data/types.py
llama_api_bench/data/usage.py
llama_api_bench/data/vision.py
llama_api_bench/models/__init__.py
llama_api_bench/models/llamaapi.py
llama_api_bench/models/openai.py
llama_api_bench/models/openrouter.py
llama_api_bench-0.0.10.dist-info/METADATA
llama_api_bench-0.0.10.dist-info/WHEEL
llama_api_bench-0.0.10.dist-info/entry_points.txt
llama_api_bench-0.0.10.dist-info/licenses/LICENSE
llama_api_bench-0.0.10.dist-info/RECORD
